{
  "success": true,
  "message": "",
  "code": 0,
  "result": {
    "total": 1,
    "records": [
      {
        "order_no": 44269986,
        "magic": 2088767545,
        "symbol": "XAUUSDzero",
        "trader_id": "1968599271295811586",
        "margin": 655858.74,
        "swap": 0.0,
        "owning_account": "2088767546",
        "open_time": "2025-09-18 12:18:30",
        "owning_userid": "1962808746181640193",
        "type": 1,
        "close_price": 3667.78,
        "jeecg_row_key": "1968605555141349378",
        "size": 1.09,
        "sl": 0.0,
        "master_order_no": 44269985,
        "commission": -8.72,
        "comment": "#QCUXT#WK_AUTO",
        "id": "1968605555141349378",
        "open_price": 3667.87,
        "tp": 0.0,
        "profit": 14.76,
        "slip_point": 0.0,
        "market_account_id": ""
      }
    ]
  },
  "timestamp": 1758187115129
}