[
  {
    "size": 0.7,
    "comment": "zdhd06231",
    "close_no": "5334902557236",
    "magical": 2917372,
    "open_price": 4202.77,
    "symbol": "XAUUSD",
    "order_no": 2917386,
    "true_total_lots": 1.4,
    "foi.order_no": "5334902557236",
    "operation_type": 1,
    "create_time": "2025-12-04 10:44:10",
    "status": 1,
    "min_lot_size": 0.0,
    "max_lot_size": 0.0,
    "total_lots": 0.7,
    "master_order": 2917372,
    "total_orders": 2
  },
  {
    "size": 0.23,
    "comment": "zdhd06231",
    "close_no": "0797756509917",
    "magical": 2917383,
    "open_price": 4202.77,
    "symbol": "XAUUSD",
    "order_no": 2917393,
    "true_total_lots": 0.46,
    "foi.order_no": "0797756509917",
    "operation_type": 1,
    "create_time": "2025-12-04 10:44:10",
    "status": 1,
    "min_lot_size": 0.0,
    "max_lot_size": 0.0,
    "total_lots": 0.23,
    "master_order": 2917383,
    "total_orders": 2
  },
  {
    "size": 0.34,
    "comment": "zdhd06231",
    "close_no": "9885544710752",
    "magical": 2917374,
    "open_price": 4202.77,
    "symbol": "XAUUSD",
    "order_no": 2917385,
    "true_total_lots": 0.68,
    "foi.order_no": "9885544710752",
    "operation_type": 1,
    "create_time": "2025-12-04 10:44:10",
    "status": 1,
    "min_lot_size": 0.0,
    "max_lot_size": 0.0,
    "total_lots": 0.34,
    "master_order": 2917374,
    "total_orders": 2
  },
  {
    "size": 0.11,
    "comment": "zdhd06231",
    "close_no": "3470835947421",
    "magical": 2917377,
    "open_price": 4202.77,
    "symbol": "XAUUSD",
    "order_no": 2917391,
    "true_total_lots": 0.22,
    "foi.order_no": "3470835947421",
    "operation_type": 1,
    "create_time": "2025-12-04 10:44:10",
    "status": 1,
    "min_lot_size": 0.0,
    "max_lot_size": 0.0,
    "total_lots": 0.11,
    "master_order": 2917377,
    "total_orders": 2
  },
  {
    "size": 0.18,
    "comment": "zdhd06231",
    "close_no": "6629699018096",
    "magical": 2917379,
    "open_price": 4202.77,
    "symbol": "XAUUSD",
    "order_no": 2917392,
    "true_total_lots": 0.36,
    "foi.order_no": "6629699018096",
    "operation_type": 1,
    "create_time": "2025-12-04 10:44:10",
    "status": 1,
    "min_lot_size": 0.0,
    "max_lot_size": 0.0,
    "total_lots": 0.18,
    "master_order": 2917379,
    "total_orders": 2
  },
  {
    "size": 0.44,
    "comment": "zdhd06231",
    "close_no": "9144220264239",
    "magical": 2917382,
    "open_price": 4202.77,
    "symbol": "XAUUSD",
    "order_no": 2917397,
    "true_total_lots": 0.88,
    "foi.order_no": "9144220264239",
    "operation_type": 1,
    "create_time": "2025-12-04 10:44:10",
    "status": 1,
    "min_lot_size": 0.0,
    "max_lot_size": 0.0,
    "total_lots": 0.44,
    "master_order": 2917382,
    "total_orders": 2
  },
  {
    "size": 0.45,
    "comment": "zdhd06231",
    "close_no": "8304802903830",
    "magical": 2917380,
    "open_price": 4202.77,
    "symbol": "XAUUSD",
    "order_no": 2917396,
    "true_total_lots": 0.9,
    "foi.order_no": "8304802903830",
    "operation_type": 1,
    "create_time": "2025-12-04 10:44:10",
    "status": 1,
    "min_lot_size": 0.0,
    "max_lot_size": 0.0,
    "total_lots": 0.45,
    "master_order": 2917380,
    "total_orders": 2
  },
  {
    "size": 0.76,
    "comment": "zdhd06231",
    "close_no": "2240912931115",
    "magical": 2917376,
    "open_price": 4202.77,
    "symbol": "XAUUSD",
    "order_no": 2917389,
    "true_total_lots": 1.52,
    "foi.order_no": "2240912931115",
    "operation_type": 1,
    "create_time": "2025-12-04 10:44:10",
    "status": 1,
    "min_lot_size": 0.0,
    "max_lot_size": 0.0,
    "total_lots": 0.76,
    "master_order": 2917376,
    "total_orders": 2
  },
  {
    "size": 0.32,
    "comment": "zdhd06231",
    "close_no": "0719821833793",
    "magical": 2917378,
    "open_price": 4202.77,
    "symbol": "XAUUSD",
    "order_no": 2917390,
    "true_total_lots": 0.64,
    "foi.order_no": "0719821833793",
    "operation_type": 1,
    "create_time": "2025-12-04 10:44:10",
    "status": 1,
    "min_lot_size": 0.0,
    "max_lot_size": 0.0,
    "total_lots": 0.32,
    "master_order": 2917378,
    "total_orders": 2
  },
  {
    "size": 0.17,
    "comment": "zdhd06231",
    "close_no": "5861200471384",
    "magical": 2917384,
    "open_price": 4202.77,
    "symbol": "XAUUSD",
    "order_no": 2917395,
    "true_total_lots": 0.34,
    "foi.order_no": "5861200471384",
    "operation_type": 1,
    "create_time": "2025-12-04 10:44:10",
    "status": 1,
    "min_lot_size": 0.0,
    "max_lot_size": 0.0,
    "total_lots": 0.17,
    "master_order": 2917384,
    "total_orders": 2
  },
  {
    "size": 0.29,
    "comment": "zdhd06231",
    "close_no": "0039982754398",
    "magical": 2917375,
    "open_price": 4202.77,
    "symbol": "XAUUSD",
    "order_no": 2917387,
    "true_total_lots": 0.58,
    "foi.order_no": "0039982754398",
    "operation_type": 1,
    "create_time": "2025-12-04 10:44:10",
    "status": 1,
    "min_lot_size": 0.0,
    "max_lot_size": 0.0,
    "total_lots": 0.29,
    "master_order": 2917375,
    "total_orders": 2
  },
  {
    "size": 0.95,
    "comment": "zdhd06231",
    "close_no": "4931915893122",
    "magical": 2917373,
    "open_price": 4202.77,
    "symbol": "XAUUSD",
    "order_no": 2917388,
    "true_total_lots": 1.9,
    "foi.order_no": "4931915893122",
    "operation_type": 1,
    "create_time": "2025-12-04 10:44:10",
    "status": 1,
    "min_lot_size": 0.0,
    "max_lot_size": 0.0,
    "total_lots": 0.95,
    "master_order": 2917373,
    "total_orders": 2
  },
  {
    "size": 0.06,
    "comment": "zdhd06231",
    "close_no": "0025291391178",
    "magical": 2917381,
    "open_price": 4202.77,
    "symbol": "XAUUSD",
    "order_no": 2917394,
    "true_total_lots": 0.12,
    "foi.order_no": "0025291391178",
    "operation_type": 1,
    "create_time": "2025-12-04 10:44:10",
    "status": 1,
    "min_lot_size": 0.0,
    "max_lot_size": 0.0,
    "total_lots": 0.06,
    "master_order": 2917381,
    "total_orders": 2
  }
]