{
  "traderId": 15541,
  "platform": "CWGMarketsSVG-Demo",
  "account": "66938917",
  "password": "4d490499c86409791b0800ba36b9665c",
  "remark": "参数化新增跟单账号",
  "followDirection": 0,
  "followMode": 1,
  "remainder": 0,
  "followParam": "1",
  "placedType": 0,
  "templateId": 1,
  "followStatus": 1,
  "followOpen": 1,
  "followClose": 1,
  "followRep": 0,
  "fixedComment": "",
  "commentType": "",
  "digits": 0,
  "cfd": "@",
  "forex": "",
  "abRemark": "",
  "followTraderSymbolEntityList": [],
  "platformType": 1
}